LICENSE
README.md
setup.py
turboguard/__init__.py
turboguard/core.c
turboguard.egg-info/PKG-INFO
turboguard.egg-info/SOURCES.txt
turboguard.egg-info/dependency_links.txt
turboguard.egg-info/top_level.txt